smartpathlibrary/__init__.py
smartpathlibrary/tools.py
smartpathlibrary-0.1.3.dist-info/licenses/LICENSE
smartpathlibrary-0.1.3.dist-info/METADATA
smartpathlibrary-0.1.3.dist-info/WHEEL
smartpathlibrary-0.1.3.dist-info/top_level.txt
smartpathlibrary-0.1.3.dist-info/RECORD
