Metadata-Version: 2.4
Name: smartpathlibrary
Version: 0.1.3
Summary: Library for working with paths to files and folders.
Home-page: https://github.com/smartlegionlab/smartpathlibrary/
Author: A.A. Suvorov
Author-email: smartlegiondev@gmail.com
License: BSD 3-Clause License
Project-URL: Documentation, https://github.com/smartlegionlab/smartpathlibrary/blob/master/README.md
Project-URL: Release notes, https://github.com/smartlegionlab/smartpathlibrary/releases
Keywords: smartpathlibrary,smartlegionlab
Classifier: Development Status :: 5 - Production/Stable
Classifier: License :: OSI Approved :: BSD License
Classifier: Natural Language :: English
Classifier: Operating System :: OS Independent
Classifier: Operating System :: POSIX :: Linux
Classifier: Programming Language :: Python :: 3 :: Only
Classifier: Topic :: Software Development :: Libraries :: Python Modules
Requires-Python: >=3.6
License-File: LICENSE
Dynamic: license-file
